MANIFEST.in
README.md
setup.py
freepybox/__init__.py
freepybox/access.py
freepybox/exceptions.py
freepybox/freepybox.py
freepybox.egg-info/PKG-INFO
freepybox.egg-info/SOURCES.txt
freepybox.egg-info/dependency_links.txt
freepybox.egg-info/requires.txt
freepybox.egg-info/top_level.txt
freepybox/api/__init__.py
freepybox/api/call.py
freepybox/api/dhcp.py
freepybox/api/fs.py
freepybox/api/fsnav.py
freepybox/api/lan.py
freepybox/api/switch.py
freepybox/api/system.py
freepybox/api/wifi.py