Metadata-Version: 1.1
Name: freepybox
Version: 0.0.2
Summary: Provides authentication and row access to Freebox using OS developer API
Home-page: https://github.com/fstercq/freepybox
Author: fstercq
Author-email: UNKNOWN
License: UNKNOWN
Keywords: freebox
Platform: UNKNOWN
Classifier: Programming Language :: Python
Classifier: Development Status :: 3 - Alpha
Classifier: License :: OSI Approved :: GNU General Public License (GPL)
Classifier: Programming Language :: Python :: 3
Classifier: Programming Language :: Python :: 3.4
Classifier: Programming Language :: Python :: 3.5
Classifier: Programming Language :: Python :: 3.6
